bioplexpy/__init__.py
bioplexpy/analysis_funcs.py
bioplexpy/data_import_funcs.py
bioplexpy/version.py
bioplexpy/visualization_funcs.py
bioplexpy-1.1.0.dist-info/METADATA
bioplexpy-1.1.0.dist-info/WHEEL
bioplexpy-1.1.0.dist-info/licenses/LICENSE
bioplexpy-1.1.0.dist-info/RECORD
