Metadata-Version: 2.4
Name: bioplexpy
Version: 1.1.0
Summary: Python-side access to PPI data from Gygi lab
Author-email: Roger Vargas <roger_vargas@g.harvard.edu>, Ludwig Geistlinger <ludwig_geistlinger@hms.harvard.edu>, Tyrone Lee <tyrone_lee@hms.harvard.edu>
License: MIT License
License-File: LICENSE
Requires-Dist: anndata
Requires-Dist: biopython
Requires-Dist: matplotlib
Requires-Dist: networkx
Requires-Dist: numpy
Requires-Dist: pandas
Requires-Dist: pypdb
Requires-Dist: requests
Requires-Dist: scipy
Provides-Extra: devel
Requires-Dist: ruff; extra == 'devel'
